AD/ADmulti.py
AD/__init__.py
AD/driver.py
AD/test_ADmulti.py
Extensions/Optimizer.py
Extensions/Test_Optimizer.py
Extensions/__init__.py
CityAD-0.1.2.dist-info/LICENSE
CityAD-0.1.2.dist-info/METADATA
CityAD-0.1.2.dist-info/WHEEL
CityAD-0.1.2.dist-info/top_level.txt
CityAD-0.1.2.dist-info/RECORD
