Metadata-Version: 2.1
Name: CityAD
Version: 0.1.2
Summary: CityAD, an Automatic Differentiation package
Home-page: https://github.com/cityscape-107/cs107-FinalProject
Author: Group CityScape
Author-email: cityad.helpline@gmail.com
License: UNKNOWN
Platform: UNKNOWN
Classifier: Programming Language :: Python :: 3
Classifier: License :: OSI Approved :: MIT License
Classifier: Operating System :: OS Independent
Requires-Python: >=3.6
Requires-Dist: numpy (==1.18.0)
